datasette_ics/__init__.py
datasette_ics/utils.py
datasette_ics-0.5.2.dist-info/LICENSE
datasette_ics-0.5.2.dist-info/METADATA
datasette_ics-0.5.2.dist-info/WHEEL
datasette_ics-0.5.2.dist-info/entry_points.txt
datasette_ics-0.5.2.dist-info/top_level.txt
datasette_ics-0.5.2.dist-info/RECORD
