Metadata-Version: 2.1
Name: datasette-ics
Version: 0.5.2
Summary: Datasette plugin for outputting iCalendar files
Home-page: https://github.com/simonw/datasette-ics
Author: Simon Willison
License: Apache License, Version 2.0
Project-URL: Issues, https://github.com/simonw/datasette-ics/issues
Project-URL: CI, https://github.com/simonw/datasette-ics/actions
Project-URL: Changelog, https://github.com/simonw/datasette-ics/releases
Classifier: Framework :: Datasette
Classifier: License :: OSI Approved :: Apache Software License
License-File: LICENSE
Requires-Dist: datasette (>=0.49)
Requires-Dist: ics (==0.7.2)
Provides-Extra: test
Requires-Dist: pytest ; extra == 'test'
Requires-Dist: pytest-asyncio ; extra == 'test'
